BrickFTP-0.5.1.dist-info/METADATA
BrickFTP-0.5.1.dist-info/RECORD
BrickFTP-0.5.1.dist-info/WHEEL
BrickFTP-0.5.1.dist-info/top_level.txt
brickftp/__init__.py
brickftp/client.py
