Metadata-Version: 2.1
Name: BrickFTP
Version: 0.5.1
Summary: Python Client for BrickFTP API (https://developers.brickftp.com/).
Home-page: https://github.com/Usio-Energy/BrickFTP
Author: Richard O'Dwyer
Author-email: richard@richard.do
License: Apache 2
Platform: UNKNOWN
Classifier: License :: OSI Approved :: Apache Software License
Classifier: Programming Language :: Python
Classifier: Programming Language :: Python :: 3
Classifier: Programming Language :: Python :: 3.6
Classifier: Programming Language :: Python :: Implementation :: CPython
Classifier: Programming Language :: Python :: Implementation :: PyPy
Requires-Python: >=3.6.0
Requires-Dist: requests (>=0.10)
Requires-Dist: wheel (>=0.30.0)
Requires-Dist: setuptools (>=39.0.1)
